.gitignore
.travis.yml
CHANGES.rst
README.rst
development.ini
setup.cfg
setup.py
kotti_quiz/__init__.py
kotti_quiz/fanstatic.py
kotti_quiz/resources.py
kotti_quiz.egg-info/PKG-INFO
kotti_quiz.egg-info/SOURCES.txt
kotti_quiz.egg-info/dependency_links.txt
kotti_quiz.egg-info/entry_points.txt
kotti_quiz.egg-info/not-zip-safe
kotti_quiz.egg-info/requires.txt
kotti_quiz.egg-info/top_level.txt
kotti_quiz/locale/kotti_quiz.pot
kotti_quiz/locale/de/LC_MESSAGES/kotti_quiz.mo
kotti_quiz/locale/de/LC_MESSAGES/kotti_quiz.po
kotti_quiz/static/quiz.js
kotti_quiz/static/style.css
kotti_quiz/templates/answerview.pt
kotti_quiz/templates/checkview.pt
kotti_quiz/templates/questionview.pt
kotti_quiz/templates/quizview.pt
kotti_quiz/templates/view.pt
kotti_quiz/tests/conftest.py
kotti_quiz/tests/test_example.py
kotti_quiz/tests/test_resources.py
kotti_quiz/tests/test_views.py
kotti_quiz/views/__init__.py
kotti_quiz/views/quiz.py