Metadata-Version: 1.1
Name: kotti-quiz
Version: 0.1
Summary: Quiz Content Type for Kotti
Home-page: https://github.com/sbabrass/kotti_quiz
Author: Sebastian Brass
Author-email: brass@xo7.de
License: BSD
Keywords: kotti addon
Platform: UNKNOWN
Classifier: Programming Language :: Python
Classifier: Framework :: Pyramid
Classifier: License :: Repoze Public License
